perftrackergt/performance.py
perftrackergt-1.0.0.dist-info/LICENSE
perftrackergt-1.0.0.dist-info/METADATA
perftrackergt-1.0.0.dist-info/WHEEL
perftrackergt-1.0.0.dist-info/top_level.txt
perftrackergt-1.0.0.dist-info/RECORD
