Metadata-Version: 2.1
Name: perftrackergt
Version: 1.0.0
Summary: Measures total execution time and memory usage. This module tests a function, providing the execution duration, initial memory footprint, and peak memory consumption throughout its run.
Author-email: Eduardo <elprogramadorgt8@gmail.com>
Project-URL: Homepage, https://github.com/elprogramadorgt/perftrackergt
Project-URL: Issues, https://github.com/elprogramadorgt/perftrackergt/issues
Classifier: Programming Language :: Python :: 3
Classifier: License :: OSI Approved :: MIT License
Classifier: Operating System :: OS Independent
Requires-Python: >=3.7
License-File: LICENSE
